reader/__init__.py
reader/reader.py
goodreads_reader-0.1.0.dist-info/METADATA
goodreads_reader-0.1.0.dist-info/WHEEL
goodreads_reader-0.1.0.dist-info/top_level.txt
goodreads_reader-0.1.0.dist-info/RECORD
