Metadata-Version: 2.1
Name: goodreads-reader
Version: 0.1.0
Summary: Library from fetching Goodreads data
Home-page: UNKNOWN
Author: Rifath Rashid
Author-email: rashid.rifath@gmail.com
License: MIT
Platform: UNKNOWN
Classifier: Intended Audience :: Developers
Classifier: License :: OSI Approved :: MIT License
Classifier: Programming Language :: Python
Classifier: Programming Language :: Python :: 3
Classifier: Programming Language :: Python :: 3.6
Classifier: Programming Language :: Python :: 3.7
Classifier: Programming Language :: Python :: 3.8
Classifier: Programming Language :: Python :: 3.9
Classifier: Operating System :: OS Independent
Requires-Dist: requests
